clidbs/__init__.py
clidbs/cli.py
clidbs/config.py
clidbs/databases.py
clidbs/notifications.py
clidbs/ssl.py
clidbs/style.py
clidbs/cmds/__init__.py
clidbs/cmds/backup_dbs.py
clidbs/cmds/db_logs.py
clidbs/cmds/db_manage.py
clidbs/cmds/db_metrics.py
clidbs/cmds/get_version.py
clidbs/cmds/list_databases.py
clidbs/cmds/list_supported.py
clidbs/cmds/reset_password.py
clidbs/cmds/ssl_management.py
clidbs/cmds/system_setup.py
clidbs/functions/__init__.py
clidbs/functions/backup_utils.py
clidbs/functions/connection_utils.py
clidbs/functions/container_utils.py
clidbs/functions/docker_utils.py
clidbs/functions/print_utils.py
clidbs/functions/security_utils.py
clidbs/functions/ssl_utils.py
clidbs/functions/utils.py
clidbs-4.26.0.dist-info/METADATA
clidbs-4.26.0.dist-info/WHEEL
clidbs-4.26.0.dist-info/entry_points.txt
clidbs-4.26.0.dist-info/RECORD
