Metadata-Version: 2.4
Name: clidbs
Version: 4.26.0
Summary: A modern CLI tool for managing databases on VPS systems with SSL support
Author: Andrew Wade
Requires-Python: >=3.8
Requires-Dist: boto3>=1.26.111
Requires-Dist: click>=8.0.0
Requires-Dist: docker>=6.1.0
Requires-Dist: packaging>=23.0
Requires-Dist: psutil>=5.9.0
Requires-Dist: pydantic>=2.0.0
Requires-Dist: python-dotenv>=1.0.0
Requires-Dist: requests>=2.31.0
Requires-Dist: rich>=13.0.0
